tilebox/workflows/__init__.py
tilebox/workflows/cache.py
tilebox/workflows/client.py
tilebox/workflows/data.py
tilebox/workflows/interceptors.py
tilebox/workflows/task.py
tilebox/workflows/timeseries.py
tilebox/workflows/automations/__init__.py
tilebox/workflows/automations/client.py
tilebox/workflows/automations/cron.py
tilebox/workflows/automations/service.py
tilebox/workflows/automations/storage_event.py
tilebox/workflows/clusters/__init__.py
tilebox/workflows/clusters/client.py
tilebox/workflows/clusters/service.py
tilebox/workflows/formatting/__init__.py
tilebox/workflows/formatting/job.py
tilebox/workflows/jobs/__init__.py
tilebox/workflows/jobs/client.py
tilebox/workflows/jobs/service.py
tilebox/workflows/observability/__init__.py
tilebox/workflows/observability/logging.py
tilebox/workflows/observability/tracing.py
tilebox/workflows/runner/__init__.py
tilebox/workflows/runner/task_runner.py
tilebox/workflows/runner/task_service.py
tilebox/workflows/workflows/v1/automation_pb2.py
tilebox/workflows/workflows/v1/automation_pb2.pyi
tilebox/workflows/workflows/v1/automation_pb2_grpc.py
tilebox/workflows/workflows/v1/core_pb2.py
tilebox/workflows/workflows/v1/core_pb2.pyi
tilebox/workflows/workflows/v1/core_pb2_grpc.py
tilebox/workflows/workflows/v1/diagram_pb2.py
tilebox/workflows/workflows/v1/diagram_pb2.pyi
tilebox/workflows/workflows/v1/diagram_pb2_grpc.py
tilebox/workflows/workflows/v1/job_pb2.py
tilebox/workflows/workflows/v1/job_pb2.pyi
tilebox/workflows/workflows/v1/job_pb2_grpc.py
tilebox/workflows/workflows/v1/task_pb2.py
tilebox/workflows/workflows/v1/task_pb2.pyi
tilebox/workflows/workflows/v1/task_pb2_grpc.py
tilebox/workflows/workflows/v1/workflows_pb2.py
tilebox/workflows/workflows/v1/workflows_pb2.pyi
tilebox/workflows/workflows/v1/workflows_pb2_grpc.py
tilebox_workflows-0.48.0.dist-info/METADATA
tilebox_workflows-0.48.0.dist-info/WHEEL
tilebox_workflows-0.48.0.dist-info/RECORD
