Metadata-Version: 2.4
Name: tilebox-workflows
Version: 0.48.0
Summary: Workflow client and task runner for Tilebox
Project-URL: Homepage, https://tilebox.com
Project-URL: Documentation, https://docs.tilebox.com/workflows/introduction
Author-email: "Tilebox, Inc." <support@tilebox.com>
License: MIT License
Classifier: Intended Audience :: Developers
Classifier: Intended Audience :: Science/Research
Classifier: License :: OSI Approved :: MIT License
Classifier: Operating System :: OS Independent
Classifier: Programming Language :: Python
Classifier: Programming Language :: Python :: 3
Classifier: Programming Language :: Python :: 3.10
Classifier: Programming Language :: Python :: 3.11
Classifier: Programming Language :: Python :: 3.12
Classifier: Programming Language :: Python :: 3.13
Classifier: Topic :: Scientific/Engineering
Classifier: Topic :: Software Development
Requires-Python: >=3.10
Requires-Dist: boto3-stubs[essential]>=1.33
Requires-Dist: boto3>=1.33
Requires-Dist: google-cloud-storage>=2.10
Requires-Dist: ipywidgets>=8.1.7
Requires-Dist: opentelemetry-api>=1.28
Requires-Dist: opentelemetry-exporter-otlp-proto-http>=1.28
Requires-Dist: opentelemetry-sdk>=1.28
Requires-Dist: python-dateutil>=2.9.0.post0
Requires-Dist: tenacity>=8
Requires-Dist: tilebox-datasets
Requires-Dist: tilebox-grpc>=0.28.0
